{
  "jana_aboelella.jpg": "Jana Aboelella",
  "liam_adam.jpg": "Liam Adam",
  "yuuki_akaike.jpg": "Yuuki Akaike",
  "jawad_alfashkhi.jpg": "Jawad Alfashkhi",
  "ali_akbar_alizada.jpg": "Ali Akbar Alizada",
  "samantha_amiri.jpg": "Samantha Amiri",
  "jimmy_campbell.jpg": "Jimmy Campbell",
  "kailen_anderson.jpg": "Kailen Anderson",
  "koan_anderson.jpg": "Koan Anderson",
  "sina_araghi.jpg": "Sina Araghi",
  "zyro_gil_areopagita.jpg": "Zyro Gil Areopagita",
  "koben_armer_petrie.jpg": "Koben Armer-Petrie",
  "daniel_arriola.jpg": "Daniel Arriola",
  "riley_cave.jpg": "Riley Cave",
  "herveen_aujla.jpg": "Herveen Aujla",
  "milos_avramovic.jpg": "Milos Avramovic",
  "kohei_awano.jpg": "Kohei Awano",
  "nicholas_awrey.jpg": "Nicholas Awrey",
  "dorsa_babaei.jpg": "Dorsa Babaei",
  "mohamed_badawy.jpg": "Mohamed Badawy",
  "cameron_chan.jpg": "Cameron Chan",
  "jennifer_bae.jpg": "Jennifer Bae",
  "heizle_bak.jpg": "Heizle Bak",
  "giovanna_baldelli.jpg": "Giovanna Baldelli",
  "kiril_baldin.jpg": "Kiril Baldin",
  "caileigh_ballantyne.jpg": "Caileigh Ballantyne",
  "cristobal_baquedano_aceituno.jpg": "Cristobal Baquedano Aceituno",
  "rachel_chau.jpg": "Rachel Chau",
  "tyson_bascombe.jpg": "Tyson Bascombe",
  "christopher_bassey.jpg": "Christopher Bassey",
  "richard_batiz.jpg": "Richard Batiz",
  "garion_bevilacqua.jpg": "Garion Bevilacqua",
  "alyaan_bhimani.jpg": "Alyaan Bhimani",
  "mayank_bhosale.jpg": "Mayank Bhosale",
  "rylan_cheng.jpg": "Rylan Cheng",
  "shaylen_bhushan.jpg": "Shaylen Bhushan",
  "ihor_boiko.jpg": "Ihor Boiko",
  "nathan_bourke.jpg": "Nathan Bourke",
  "nicholas_boy.jpg": "Nicholas Boy",
  "alessia_bruno.jpg": "Alessia Bruno",
  "rui_cabrita.jpg": "Rui Cabrita",
  "aleina_cho.jpg": "Aleina Cho",
  "mario_capolongo.jpg": "Mario Capolongo",
  "dario_cappelletti.jpg": "Dario Cappelletti",
  "nico_caputo.jpg": "Nico Caputo",
  "chiara_carioti.jpg": "Chiara Carioti",
  "natan_castro.jpg": "Natan Castro",
  "marco_cazabon.jpg": "Marco Cazabon",
  "guo_cen.jpg": "Guo Cen",
  "kai_chalmers.jpg": "Kai Chalmers",
  "ally_chan.jpg": "Ally Chan",
  "cadence_chan.jpg": "Cadence Chan",
  "carter_chan.jpg": "Carter Chan",
  "eiden_chan.jpg": "Eiden Chan",
  "eitan_chan.jpg": "Eitan Chan",
  "kurtis_chan.jpg": "Kurtis Chan",
  "makenna_chan.jpg": "Makenna Chan",
  "isabella_chen.jpg": "Isabella Chen",
  "isabella_cheng.jpg": "Isabella Cheng",
  "jasper_cheng.jpg": "Jasper Cheng",
  "keira_cheng.jpg": "Keira Cheng",
  "nadia_cheng.jpg": "Nadia Cheng",
  "tyler_cheng.jpg": "Tyler Cheng",
  "marcus_cheung.jpg": "Marcus Cheung",
  "lian_chichioco.jpg": "Lian Chichioco",
  "luc_chien.jpg": "Luc Chien",
  "sofia_chin.jpg": "Sofia Chin",
  "naphtali_cho.jpg": "Naphtali Cho",
  "harang_choi.jpg": "Harang Choi",
  "nathanael_chong.jpg": "Nathanael Chong",
  "mark_chow.jpg": "Mark Chow",
  "ryan_chow.jpg": "Ryan Chow",
  "hailey_chu.jpg": "Hailey Chu",
  "sherwin_chui.jpg": "Sherwin Chui",
  "elijah_clarke.jpg": "Elijah Clarke",
  "dante_combatti.jpg": "Dante Combatti",
  "noah_cruz.jpg": "Noah Cruz",
  "ella_csabai.jpg": "Ella Csabai",
  "erik_flormata.jpg": "Erik Flormata",
  "erin_curley.jpg": "Erin Curley",
  "kien_hao_dang.jpg": "Kien Hao Dang",
  "maeve_dawson.jpg": "Maeve Dawson",
  "kamran_daya.jpg": "Kamran Daya",
  "markus_delorme.jpg": "Markus Delorme",
  "jiya_dhinsa.jpg": "Jiya Dhinsa",
  "ali_ghandharian.jpg": "Ali Ghandharian",
  "anna_dianov.jpg": "Anna Dianov",
  "kira_dias.jpg": "Kira Dias",
  "astor_diaz_garcia.jpg": "Astor Diaz Garcia",
  "rihanna_ding.jpg": "Rihanna Ding",
  "peter_dong.jpg": "Peter Dong",
  "colin_du.jpg": "Colin Du",
  "ali_hassan.jpg": "Ali Hassan",
  "bradley_duncan.jpg": "Bradley Duncan",
  "rj_ebrao.jpg": "R.J. Ebrao",
  "neth_ekanayake.jpg": "Neth Ekanayake",
  "saisha_ray_espinosa.jpg": "Saisha Ray Espinosa",
  "tona_eto.jpg": "Tona Eto",
  "anthony_faccone.jpg": "Anthony Faccone",
  "alexandru_hodut.jpg": "Alexandru Hodut",
  "louise_fan.jpg": "Louise Fan",
  "rico_fan.jpg": "Rico Fan",
  "eddie_fang.jpg": "Eddie Fang",
  "amirali_fathisardehaee.jpg": "Amirali Fathisardehaee",
  "mikaylia_fearon.jpg": "Mikaylia Fearon",
  "vlada_fedorova.jpg": "Vlada Fedorova",
  "emerson_huang.jpg": "Emerson Huang",
  "elexandria_feeny.jpg": "Elexandria Feeny",
  "karen_feng.jpg": "Karen Feng",
  "mike_feng.jpg": "Mike Feng",
  "yilin_feng.jpg": "Yilin Feng",
  "sebastian_ferraro.jpg": "Sebastian Ferraro",
  "alicia_flores_granados.jpg": "Alicia Flores Granados",
  "ethan_huang.jpg": "Ethan Huang",
  "evelyn_jocol_garcia.jpg": "Evelyn Jocol Garcia",
  "layla_johnson.jpg": "Layla Johnson",
  "mia_jukic.jpg": "Mia Jukic",
  "jack_jung.jpg": "Jack Jung",
  "lua_jung.jpg": "Lua Jung",
  "tymur_kalashnikov.jpg": "Tymur Kalashnikov",
  "joseph_lecce.jpg": "Joseph Lecce",
  "aarini_kalia.jpg": "Aarini Kalia",
  "kyron_kan.jpg": "Kyron Kan",
  "euan_kang.jpg": "Euan Kang",
  "chandramouli_karthik.jpg": "Chandramouli Karthik",
  "madison_kennedy.jpg": "Madison Kennedy",
  "aspen_kent.jpg": "Aspen Kent",
  "owen_lee.jpg": "Owen Lee",
  "john_kim.jpg": "John Kim",
  "juheon_kim.jpg": "Juheon Kim",
  "olivia_kim.jpg": "Olivia Kim",
  "steve_kim.jpg": "Steve Kim",
  "yunchan_kim.jpg": "Yunchan Kim",
  "hayden_kok.jpg": "Hayden Kok",
  "garett_leong.jpg": "Garett Leong",
  "angel_kooner.jpg": "Angel Kooner",
  "simon_kosik.jpg": "Simon Kosik",
  "celine_kostanian.jpg": "Celine Kostanian",
  "joey_kowalenko.jpg": "Joey Kowalenko",
  "sofija_kresic.jpg": "Sofija Kresic",
  "kegham_kullahian.jpg": "Kegham Kullahian",
  "brayden_lin.jpg": "Brayden Lin",
  "ethan_kuypers.jpg": "Ethan Kuypers",
  "camilah_kwan.jpg": "Camilah Kwan",
  "evan_kwok.jpg": "Evan Kwok",
  "kaden_kwok.jpg": "Kaden Kwok",
  "jiro_kyuse.jpg": "Jiro Kyuse",
  "lucas_lakovic.jpg": "Lucas Lakovic",
  "marcus_lui.jpg": "Marcus Lui",
  "carissa_lam.jpg": "Carissa Lam",
  "jordan_lam.jpg": "Jordan Lam",
  "kaitlyn_lam.jpg": "Kaitlyn Lam",
  "sammi_lam.jpg": "Sammi Lam",
  "dylan_launt.jpg": "Dylan Launt",
  "nicole_leblanc.jpg": "Nicole LeBlanc",
  "marcus_mah.jpg": "Marcus Mah",
  "candi_lee.jpg": "Candi Lee",
  "chloe_lee.jpg": "Chloe Lee",
  "jayden_lee.jpg": "Jayden Lee",
  "mackenzie_lee.jpg": "Mackenzie Lee",
  "matthew_lee.jpg": "Matthew Lee",
  "philip_lee.jpg": "Philip Lee",
  "sarah_lee.jpg": "Sarah Lee",
  "sean_lee.jpg": "Sean Lee",
  "seungwoo_lee.jpg": "Seungwoo Lee",
  "sujin_lee.jpg": "Sujin Lee",
  "ethan_leung.jpg": "Ethan Leung",
  "ariel_li.jpg": "Ariel Li",
  "sophie_li.jpg": "Sophie Li",
  "cole_lightheart.jpg": "Cole Lightheart",
  "mina_lim.jpg": "Mina Lim",
  "anson_liu.jpg": "Anson Liu",
  "selina_liu.jpg": "Selina Liu",
  "winnie_liu.jpg": "Winnie Liu",
  "keira_lo.jpg": "Keira Lo",
  "alex_lu.jpg": "Alex Lu",
  "winsy_luu.jpg": "Winsy Luu",
  "jacqueline_ma.jpg": "Jacqueline Ma",
  "ryley_macdonald.jpg": "Ryley MacDonald",
  "ashley_mah.jpg": "Ashley Mah",
  "lauryn_mah.jpg": "Lauryn Mah",
  "sophia_mak.jpg": "Sophia Mak",
  "adriana_manzi.jpg": "Adriana Manzi",
  "gabriella_manzi.jpg": "Gabriella Manzi",
  "dante_mariutti.jpg": "Dante Mariutti",
  "robbie_martignago.jpg": "Robbie Martignago",
  "cristian_pedraza_moreno.jpg": "Cristian Pedraza Moreno",
  "amadeo_perizzolo.jpg": "Amadeo Perizzolo",
  "sonja_perperidis.jpg": "Sonja Perperidis",
  "mila_perrotta.jpg": "Mila Perrotta",
  "benjamin_peter.jpg": "Benjamin Peter",
  "kyle_peters.jpg": "Kyle Peters",
  "joshua_pham.jpg": "Joshua Pham",
  "nevea_pham.jpg": "Nevea Pham",
  "sarah_pimentel.jpg": "Sarah Pimentel",
  "brodie_pollak.jpg": "Brodie Pollak",
  "viktoriia_popovych.jpg": "Viktoriia Popovych",
  "eila_prasad.jpg": "Eila Prasad",
  "amisha_puri.jpg": "Amisha Puri",
  "amy_qian.jpg": "Amy Qian",
  "vivian_qian.jpg": "Vivian Qian",
  "emily_qiao.jpg": "Emily Qiao",
  "benjamin_qiu.jpg": "Benjamin Qiu",
  "fayyad_quazi.jpg": "Fayyad Quazi",
  "antonia_rad.jpg": "Antonia Rad",
  "mahbod_rafiee.jpg": "Mahbod Rafiee",
  "sara_ramadan.jpg": "Sara Ramadan",
  "tala_ramadan.jpg": "Tala Ramadan",
  "daniel_ramos_bendezu.jpg": "Daniel Ramos Bendezu",
  "mia_razzaghi.jpg": "Mia Razzaghi",
  "leah_reid.jpg": "Leah Reid",
  "gael_rivas.jpg": "Gael Rivas",
  "alejandro_roa.jpg": "Alejandro Roa",
  "sebastian_robles.jpg": "Sebastian Robles",
  "fatima_romero.jpg": "Fatima Romero",
  "adriana_rossi.jpg": "Adriana Rossi",
  "percy_routh.jpg": "Percy Routh",
  "madeline_rugge.jpg": "Madeline Rugge",
  "antonio_russo.jpg": "Antonio Russo",
  "giuseppe_russo.jpg": "Giuseppe Russo",
  "tyler_ryder.jpg": "Tyler Ryder",
  "hailey_ryu.jpg": "Hailey Ryu",
  "tawhid_safi.jpg": "Tawhid Safi",
  "georgia_sak.jpg": "Georgia Sak",
  "anmar_samara.jpg": "Anmar Samara",
  "raquel_santos.jpg": "Raquel Santos",
  "jon_sartori.jpg": "Jon Sartori",
  "abdel_rahman_sayed_ahmed.jpg": "Abdel Rahman Sayed Ahmed",
  "brenden_wang.jpg": "Brenden Wang",
  "alexander_scarcelli.jpg": "Alexander Scarcelli",
  "johnny_shen.jpg": "Johnny Shen",
  "melissa_shen.jpg": "Melissa Shen",
  "stephen_shen.jpg": "Stephen Shen",
  "joon_shin.jpg": "Joon Shin",
  "reza_shivji.jpg": "Reza Shivji",
  "bill_wei.jpg": "Bill Wei",
  "keira_shum.jpg": "Keira Shum",
  "natasa_simunovic.jpg": "Natasa Simunovic",
  "nirmay_singh.jpg": "Nirmay Singh",
  "lar_sisrian.jpg": "Lar Sisrian",
  "ethan_song.jpg": "Ethan Song",
  "izaan_soomro.jpg": "Izaan Soomro",
  "brandon_wong.jpg": "Brandon Wong",
  "galleni_stefanidis.jpg": "Galleni Stefanidis",
  "miranda_sun.jpg": "Miranda Sun",
  "ivan_sung.jpg": "Ivan Sung",
  "drew_sutherland.jpg": "Drew Sutherland",
  "diego_sverzut.jpg": "Diego Sverzut",
  "nathan_tan.jpg": "Nathan Tan",
  "regina_xu.jpg": "Regina Xu",
  "sam_tomada.jpg": "Sam Tomada",
  "jayden_tran.jpg": "Jayden Tran",
  "kael_tran.jpg": "Kael Tran",
  "sophia_tran.jpg": "Sophia Tran",
  "marcus_tse.jpg": "Marcus Tse",
  "kesler_vaesen.jpg": "Kesler Vaesen",
  "max_ye.jpg": "Max Ye",
  "hayden_valentine.jpg": "Hayden Valentine",
  "massimo_valiante.jpg": "Massimo Valiante",
  "lochlann_van_horn.jpg": "Lochlann Van Horn",
  "cohen_vigliotti.jpg": "Cohen Vigliotti",
  "mardin_vizheh.jpg": "Mardin Vizheh",
  "razik_walji.jpg": "Razik Walji",
  "beck_yu.jpg": "Beck Yu",
  "jack_wang.jpg": "Jack Wang",
  "lucas_wang.jpg": "Lucas Wang",
  "wilson_wang.jpg": "Wilson Wang",
  "emma_warnick.jpg": "Emma Warnick",
  "kyle_watson.jpg": "Kyle Watson",
  "thalia_sophie_weppler.jpg": "Thalia Sophie Weppler",
  "joseph_williams.jpg": "Joseph Williams",
  "evan_woll_glowa.jpg": "Evan Woll-Glowa",
  "antonio_wong.jpg": "Antonio Wong",
  "athena_wong.jpg": "Athena Wong",
  "kirika_wong.jpg": "Kirika Wong",
  "nicholas_woo.jpg": "Nicholas Woo",
  "yejun_woo.jpg": "Yejun Woo",
  "aiden_wood.jpg": "Aiden Wood",
  "leah_wu.jpg": "Leah Wu",
  "anson_yan.jpg": "Anson Yan",
  "jaymie_yang.jpg": "Jaymie Yang",
  "jerry_yang.jpg": "Jerry Yang",
  "molly_yang.jpg": "Molly Yang",
  "matthew_yap.jpg": "Matthew Yap",
  "lucas_yeo_chi_kai.jpg": "Lucas Yeo Chi Kai",
  "helena_yeung.jpg": "Helena Yeung",
  "sophie_yim.jpg": "Sophie Yim",
  "delphine_yip.jpg": "Delphine Yip",
  "david_yoo.jpg": "David Yoo",
  "hui_yu.jpg": "Hui Yu",
  "reem_zeidi.jpg": "Reem Zeidi",
  "juan_alberto_zertuche_garza.jpg": "Juan Alberto Zertuche Garza",
  "asher_zhang.jpg": "Asher Zhang",
  "beini_zhang.jpg": "Beini Zhang",
  "ethan_zhang.jpg": "Ethan Zhang",
  "michelle_zhang.jpg": "Michelle Zhang",
  "miffy_zhang.jpg": "Miffy Zhang",
  "vera_zhang.jpg": "Vera Zhang",
  "zhirong_zhang.jpg": "Zhirong Zhang",
  "amy_zhao.jpg": "Amy Zhao",
  "koby_zheng.jpg": "Koby Zheng",
  "chester_zhong.jpg": "Chester Zhong",
  "daniel_zhou.jpg": "Daniel Zhou",
  "selina_zhou.jpg": "Selina Zhou",
  "anna_zhu.jpg": "Anna Zhu",
  "david_zhu.jpg": "David Zhu",
  "alisa_zong.jpg": "Alisa Zong",
  "fiona_zou.jpg": "Fiona Zou"
}